inichord/__init__.py
inichord/__main__.py
inichord/__main__.ui
inichord/Auto_Denoising.py
inichord/Auto_Denoising.ui
inichord/Batch_Processing.py
inichord/Batch_Processing.ui
inichord/BM3D.py
inichord/BM3D.ui
inichord/config.txt
inichord/Contour_Map.py
inichord/Contour_Map.ui
inichord/Denoise_2Dmap.py
inichord/Denoise_2Dmap.ui
inichord/Edit_Tools.py
inichord/Edit_Tools.ui
inichord/Extract_Mosaic.py
inichord/Extract_Mosaic.ui
inichord/General_Functions.py
inichord/Grain_Treatment.py
inichord/Grain_Treatment.ui
inichord/icons/alignment_icon.png
inichord/icons/Arrow_down.png
inichord/icons/Arrow_up.png
inichord/icons/background_icon.png
inichord/icons/Check_hover_icon.png
inichord/icons/Check_icon.png
inichord/icons/crop_icon.png
inichord/icons/Export.png
inichord/icons/Eye.png
inichord/icons/filter_icon.png
inichord/icons/Grain_Icons.png
inichord/icons/import_icon.png
inichord/icons/Indexation_icon.png
inichord/icons/Main_icon.png
inichord/icons/reload_icon.png
inichord/icons/remove_outliers_icon.png
inichord/icons/Restored_Icons.png
inichord/icons/run_icon.png
inichord/icons/save_icon.png
inichord/icons/Stitch_icon.png
inichord/icons/Stitch_path.png
inichord/icons/Uncheck_hover_icon.png
inichord/icons/Uncheck_icon.png
inichord/iniCHORD.spec
inichord/iniCHORD_GPU.spec
inichord/KAD_Function.py
inichord/Kmean.py
inichord/Kmean.ui
inichord/NLMD.py
inichord/NLMD.ui
inichord/Profile_Modification.py
inichord/Registration.py
inichord/Registration.ui
inichord/Remove_FFT.py
inichord/Remove_FFT.ui
inichord/Remove_Outliers.py
inichord/Remove_Outliers.ui
inichord/Restored_Grains.py
inichord/Restored_Grains.ui
inichord/ThreeD_Stitching.py
inichord/ThreeD_Stitching.ui
inichord/TV.py
inichord/TV.ui
inichord/TwoD_Stitching.py
inichord/TwoD_Stitching.ui
inichord/VSNR.py
inichord/VSNR.ui
inichord-0.1.31.dist-info/entry_points.txt
inichord-0.1.31.dist-info/LICENSE
inichord-0.1.31.dist-info/METADATA
inichord-0.1.31.dist-info/WHEEL
inichord-0.1.31.dist-info/RECORD
