Metadata-Version: 2.1
Name: inichord
Version: 0.1.31
Summary: image series treatment tools
License: CeCILL
Author: Gabriel Denhez L'Hôte
Author-email: glhote@insa-lyon.fr
Requires-Python: >=3.8.0,<4.0.0
Classifier: License :: Other/Proprietary License
Classifier: Programming Language :: Python :: 3
Classifier: Programming Language :: Python :: 3.8
Classifier: Programming Language :: Python :: 3.9
Classifier: Programming Language :: Python :: 3.10
Classifier: Programming Language :: Python :: 3.11
Classifier: Programming Language :: Python :: 3.12
Requires-Dist: bm3d
Requires-Dist: h5py (>=3.11,<4.0)
Requires-Dist: largestinteriorrectangle (>=0.2,<0.3)
Requires-Dist: numpy (>=1.23,<2.0)
Requires-Dist: opencv-python (>=4.10,<5.0)
Requires-Dist: pyqt5 (>=5.15,<6.0)
Requires-Dist: pyqtgraph (>=0.13,<0.14)
Requires-Dist: pystackreg (>=0.2,<0.3)
Requires-Dist: pyvsnr (>=2.2.0,<3.0.0)
Requires-Dist: scikit-image (>=0.24)
Requires-Dist: scikit-learn (>=1.5,<2.0)
Requires-Dist: scipy (>=1.14,<2.0)
